LICENSE
README.md
pyproject.toml
setup.py
drf_htmx_renderer.egg-info/PKG-INFO
drf_htmx_renderer.egg-info/SOURCES.txt
drf_htmx_renderer.egg-info/dependency_links.txt
drf_htmx_renderer.egg-info/requires.txt
drf_htmx_renderer.egg-info/top_level.txt
htmx_renderer/__init__.py
htmx_renderer/adapters.py
htmx_renderer/admin.py
htmx_renderer/apps.py
htmx_renderer/exception_handler.py
htmx_renderer/models.py
htmx_renderer/renderers.py
htmx_renderer/serializers.py
htmx_renderer/tests.py
htmx_renderer/views.py