Metadata-Version: 2.1
Name: drf-htmx-renderer
Version: 0.0.2
Summary: HTMX renderer for Django REST FRAMEWORK
Author-email: Emmanuelle Delescolle <info@levit.be>
License: MIT License
Project-URL: Homepage, https://github.com/nanuxbe/drf_htmx_renderer
Classifier: Environment :: Web Environment
Classifier: Framework :: Django
Classifier: Framework :: Django :: 3.2
Classifier: Framework :: Django :: 4.2
Classifier: Intended Audience :: Developers
Classifier: License :: OSI Approved :: MIT License
Classifier: Operating System :: OS Independent
Classifier: Programming Language :: Python
Classifier: Programming Language :: Python :: 3
Classifier: Programming Language :: Python :: 3.10
Classifier: Topic :: Internet :: WWW/HTTP
Classifier: Topic :: Internet :: WWW/HTTP :: Dynamic Content
Requires-Python: >=3.8
License-File: LICENSE
